polyase/__init__.py
polyase/allele_utils.py
polyase/ase_data_loader.py
polyase/cli.py
polyase/filter.py
polyase/multimapping.py
polyase/plotting.py
polyase/stats.py
polyase/structure.py
polyase-1.0.1.dist-info/METADATA
polyase-1.0.1.dist-info/WHEEL
polyase-1.0.1.dist-info/licenses/LICENSE
polyase-1.0.1.dist-info/RECORD
